CHANGES.txt
MANIFEST.in
README.md
requirements.cfg
setup.cfg
setup.py
src/scripts/smart_learn.py
src/MachineLearningForTextcategory/__init__.py
src/MachineLearningForTextcategory/data.py
src/MachineLearningForTextcategory/logger.py
src/MachineLearningForTextcategory/model.py
src/MachineLearningForTextcategory/prediction.py
src/MachineLearningForTextcategory.egg-info/PKG-INFO
src/MachineLearningForTextcategory.egg-info/SOURCES.txt
src/MachineLearningForTextcategory.egg-info/dependency_links.txt
src/MachineLearningForTextcategory.egg-info/requires.txt
src/MachineLearningForTextcategory.egg-info/top_level.txt
src/scripts/smart_learn.py